Workbook

Sheet Resumo & Indicadores
A1: Arroboboi Ateliê - Base de Dados Operacional
A2: Visão Geral do Sistema e Indicadores Chave de Desempenho (KPIs)
A4: Estatísticas da Base de Dados
A5: Tabela / Entidade | B5: Descrição da Entidade | C5: Total de Registros
A6: Categorias | B6: Categorias de produtos no catálogo (Umbanda, Candomblé, Wicca, etc.) | C6: =COUNTA(Categorias!A2:A7)
A7: Produtos (Catálogo) | B7: Produtos finais artesanais cadastrados | C7: =COUNTA(Produtos!A2:A501)
A8: Matérias-Primas | B8: Insumos, miçangas, búzios, pedras e matérias-primas em estoque | C8: =COUNTA(Materias_Primas!A2:A501)
A9: Fornecedores | B9: Parceiros e fornecedores de insumos | C9: =COUNTA(Fornecedores!A2:A501)
A10: Fornecedor x Matéria-Prima | B10: Vínculos de fornecimento e histórico de preços de compra | C10: =COUNTA(Fornecedor_Materia_Prima!A2:A501)
A11: Composição Produto (BOM) | B11: Ficha técnica / receita de matérias-primas por produto final | C11: =COUNTA(Composicao_Produto!A2:A501)
A12: Clientes | B12: Clientes cadastrados com contatos de WhatsApp e Instagram | C12: =COUNTA(Clientes!A2:A501)
A13: Pedidos & Orçamentos | B13: Orçamentos e pedidos de vendas registrados | C13: =COUNTA(Pedidos!A2:A501)
A14: Itens de Pedido | B14: Detalhamento dos produtos consumidos em cada pedido | C14: =COUNTA(Itens_Pedido!A2:A501)
A15: Total Geral de Registros | C15: =SUM(C6:C14)

Sheet Fornecedores
A1: id_fornecedor | B1: nome_empresa | C1: nome_contato | D1: telefone | E1: email | F1: cnpj_cpf | G1: data_cadastro
A2: 1 | B2: Distribuidora Sagrado Insumos 1 | C2: Contato 1 | D2: (11) 980000001 | E2: fornecedor1@arroboboifornecedores.com.br | F2: 00000000000001 | G2: 45659
A3: 2 | B3: Importadora Ori 2 | C3: Contato 2 | D3: (11) 980000002 | E3: fornecedor2@arroboboifornecedores.com.br | F3: 00000000000002 | G3: 45660
A4: 3 | B4: Feira Artesanal Axé Comércio 3 | C4: Contato 3 | D4: (11) 980000003 | E4: fornecedor3@arroboboifornecedores.com.br | F4: 00000000000003 | G4: 45661
A5: 4 | B5: Atacado de Artefatos Luz do Oriente 4 | C5: Contato 4 | D5: (11) 980000004 | E5: fornecedor4@arroboboifornecedores.com.br | F5: 00000000000004 | G5: 45662
A6: 5 | B6: Pedras & Metais Encanto dos Orixás 5 | C6: Contato 5 | D6: (11) 980000005 | E6: fornecedor5@arroboboifornecedores.com.br | F6: 00000000000005 | G6: 45663
A7: 6 | B7: Armarinho Fundanga 6 | C7: Contato 6 | D7: (11) 980000006 | E7: fornecedor6@arroboboifornecedores.com.br | F7: 00000000000006 | G7: 45664
A8: 7 | B8: Distribuidora Elementos da Terra 7 | C8: Contato 7 | D8: (11) 980000007 | E8: fornecedor7@arroboboifornecedores.com.br | F8: 00000000000007 | G8: 45665
A9: 8 | B9: Importadora Fios & Contas 8 | C9: Contato 8 | D9: (11) 980000008 | E9: fornecedor8@arroboboifornecedores.com.br | F9: 00000000000008 | G9: 45666
A10: 9 | B10: Feira Artesanal Abaçá Insumos 9 | C10: Contato 9 | D10: (11) 980000009 | E10: fornecedor9@arroboboifornecedores.com.br | F10: 00000000000009 | G10: 45667
A11: 10 | B11: Atacado de Artefatos Egbé 10 | C11: Contato 10 | D11: (11) 980000010 | E11: fornecedor10@arroboboifornecedores.com.br | F11: 00000000000010 | G11: 45668
A12: 11 | B12: Pedras & Metais Sagrado Insumos 11 | C12: Contato 11 | D12: (11) 980000011 | E12: fornecedor11@arroboboifornecedores.com.br | F12: 00000000000011 | G12: 45669
A13: 12 | B13: Armarinho Ori 12 | C13: Contato 12 | D13: (11) 980000012 | E13: fornecedor12@arroboboifornecedores.com.br | F13: 00000000000012 | G13: 45670
... A501: 500 | B501: Importadora Egbé 500 | C501: Contato 500 | D501: (11) 980000500 | E501: fornecedor500@arroboboifornecedores.com.br | F501: 00000000000500 | G501: 45793

Sheet Materias_Primas
A1: id_materia_prima | B1: nome | C1: unidade_medida | D1: quantidade_estoque | E1: estoque_minimo | F1: custo_unitario_medio
A2: 1 | B2: Miçangão 8/0 Azul Escuro - Lote 101 | C2: kg | D2: 13.5 | E2: 6 | F2: 3.75
A3: 2 | B3: Firma de Louça Vermelho - Lote 102 | C3: un | D3: 17 | E3: 7 | F3: 5
A4: 3 | B4: Firma de Vidro Branco - Lote 103 | C4: m | D4: 20.5 | E4: 8 | F4: 6.25
A5: 4 | B5: Búzio Africano Amarelo - Lote 104 | C5: pacote | D5: 24 | E5: 9 | F5: 7.5
A6: 5 | B6: Búzio Fechado Verde - Lote 105 | C6: g | D6: 27.5 | E6: 10 | F6: 8.75
A7: 6 | B7: Fio de Cordoalha Roxo - Lote 106 | C7: kg | D7: 31 | E7: 11 | F7: 10
A8: 7 | B8: Fio de Nylon 0.50mm Preto - Lote 107 | C8: un | D8: 34.5 | E8: 12 | F8: 11.25
A9: 8 | B9: Palha da Costa Dourado - Lote 108 | C9: m | D9: 38 | E9: 13 | F9: 12.5
A10: 9 | B10: Pedra Natural Cristal Prateado - Lote 109 | C10: pacote | D10: 41.5 | E10: 14 | F10: 13.75
A11: 10 | B11: Pedra Natural Hematita Coral - Lote 110 | C11: g | D11: 45 | E11: 15 | F11: 15
A12: 11 | B12: Pedra Natural Jaspe Red Multicolor - Lote 111 | C12: kg | D12: 48.5 | E12: 16 | F12: 16.25
A13: 12 | B13: Pingente Espada de Ogum Azul Claro - Lote 112 | C13: un | D13: 52 | E13: 17 | F13: 17.5
... A501: 500 | B501: Miçanga Jablonex 6/0 Dourado - Lote 600 | C501: g | D501: 1760 | E501: 5 | F501: 2.5

Sheet Fornecedor_Materia_Prima
A1: id_fornecedor | B1: id_materia_prima | C1: preco_ultima_compra | D1: data_ultima_compra
A2: 1 | B2: 1 | C2: 4.5 | D2: 46022
A3: 2 | B3: 2 | C3: 6 | D3: 46021
A4: 3 | B4: 3 | C4: 7.5 | D4: 46020
A5: 4 | B5: 4 | C5: 9 | D5: 46019
A6: 5 | B6: 5 | C6: 10.5 | D6: 46018
A7: 6 | B7: 6 | C7: 12 | D7: 46017
A8: 7 | B8: 7 | C8: 13.5 | D8: 46016
A9: 8 | B9: 8 | C9: 15 | D9: 46015
A10: 9 | B10: 9 | C10: 16.5 | D10: 46014
A11: 10 | B11: 10 | C11: 18 | D11: 46013
A12: 11 | B12: 11 | C12: 19.5 | D12: 46012
A13: 12 | B13: 12 | C13: 21 | D13: 46011
... A501: 500 | B501: 500 | C501: 33 | D501: 45523

Sheet Categorias
A1: id_categoria | B1: nome | C1: descricao
A2: 1 | B2: Guias Simples 1 Fio | C2: Guias de proteção e conexão em fio único de miçangas, cristais ou elementos naturais.
A3: 2 | B3: Brajás e Guias Multifios | C3: Guias robustas de 3 a 14 fios com trançados, firmas importadas e búzios africanos.
A4: 3 | B4: Acessórios e Patuás | C4: Pulseiras, chicotes, patuás de proteção e colares sagrados.
A5: 4 | B5: Altar e Utilitários Rituais | C5: Taças decoradas, castiçais, incensários e itens para consagração de altares.
A6: 5 | B6: Ferramentas e Símbolos | C6: Ferramentas dos Orixás e Entidades em escala artesanal, como tridentes e abebês.
A7: 6 | B7: Wicca e Sagrado Feminino | C7: Artefatos dedicados à egrégora neopagã, cultos à Deusa, pentáculos e caixas de consagração.

Sheet Produtos
A1: id_produto | B1: codigo_sku | C1: nome | D1: id_categoria | E1: descricao | F1: preco_venda | G1: link_instagram | H1: quantidade_estoque | I1: ativo | J1: data_cadastro
A2: 1 | B2: ARB-C2-0001 | C2: Brajá de Búzios Ogum com Búzios Africanos | D2: 2 | E2: Item confecionado artesanalmente pelo Ateliê Arroboboi para a egrégora de Ogum. Produto final de alta qualidade. | F2: 39.5 | G2: https://www.instagram.com/arroboboi.atelie/p/post_1/ | H2: 6 | I2: TRUE | J2: 45810
A3: 2 | B3: ARB-C3-0002 | C3: Pulseira Consagrada Iemanjá Trançado Especial 7 Fios | D3: 3 | E3: Item confecionado artesanalmente pelo Ateliê Arroboboi para a egrégora de Iemanjá. Produto final de alta qualidade. | F3: 44 | G3: https://www.instagram.com/arroboboi.atelie/p/post_2/ | H3: 7 | I3: TRUE | J3: 45811
A4: 3 | B4: ARB-C4-0003 | C4: Chicote de Firma Oxum com Pingente Niquelado | D4: 4 | E4: Item confecionado artesanalmente pelo Ateliê Arroboboi para a egrégora de Oxum. Produto final de alta qualidade. | F4: 48.5 | G4: https://www.instagram.com/arroboboi.atelie/p/post_3/ | H4: 8 | I4: TRUE | J4: 45812
A5: 4 | B5: ARB-C5-0004 | C5: Patuá de Proteção Xangô Edição Limitada Arroboboi | D5: 5 | E5: Item confecionado artesanalmente pelo Ateliê Arroboboi para a egrégora de Xangô. Produto final de alta qualidade. | F5: 53 | G5: https://www.instagram.com/arroboboi.atelie/p/post_4/ | H5: 9 | I5: TRUE | J5: 45813
A6: 5 | B6: ARB-C6-0005 | C6: Taça Rituística Iansã Acabamento Ouro Velho | D6: 6 | E6: Item confecionado artesanalmente pelo Ateliê Arroboboi para a egrégora de Iansã. Produto final de alta qualidade. | F6: 57.5 | G6: https://www.instagram.com/arroboboi.atelie/p/post_5/ | H6: 10 | I6: TRUE | J6: 45814
A7: 6 | B7: ARB-C1-0006 | C7: Incensário de Cerâmica Oxóssi Consagrado com Ervas | D7: 1 | E7: Item confecionado artesanalmente pelo Ateliê Arroboboi para a egrégora de Oxóssi. Produto final de alta qualidade. | F7: 62 | G7: https://www.instagram.com/arroboboi.atelie/p/post_6/ | H7: 11 | I7: TRUE | J7: 45815
A8: 7 | B8: ARB-C2-0007 | C8: Pentáculo de Madeira Obaluaê Com Cordão de Cordoalha | D8: 2 | E8: Item confecionado artesanalmente pelo Ateliê Arroboboi para a egrégora de Obaluaê. Produto final de alta qualidade. | F8: 66.5 | G8: https://www.instagram.com/arroboboi.atelie/p/post_7/ | H8: 12 | I8: TRUE | J8: 45816
A9: 8 | B9: ARB-C3-0008 | C9: Ferramenta de Metal Nana Buruku com Firma e Cristais | D9: 3 | E9: Item confecionado artesanalmente pelo Ateliê Arroboboi para a egrégora de Nana Buruku. Produto final de alta qualidade. | F9: 71 | G9: https://www.instagram.com/arroboboi.atelie/p/post_8/ | H9: 13 | I9: TRUE | J9: 45817
A10: 9 | B10: ARB-C4-0009 | C10: Guia de Miçangas Exu com Búzios Africanos | D10: 4 | E10: Item confecionado artesanalmente pelo Ateliê Arroboboi para a egrégora de Exu. Produto final de alta qualidade. | F10: 75.5 | G10: https://www.instagram.com/arroboboi.atelie/p/post_9/ | H10: 14 | I10: TRUE | J10: 45818
A11: 10 | B11: ARB-C5-0010 | C11: Brajá de Búzios Pombagira Trançado Especial 7 Fios | D11: 5 | E11: Item confecionado artesanalmente pelo Ateliê Arroboboi para a egrégora de Pombagira. Produto final de alta qualidade. | F11: 80 | G11: https://www.instagram.com/arroboboi.atelie/p/post_10/ | H11: 15 | I11: TRUE | J11: 45819
A12: 11 | B12: ARB-C6-0011 | C12: Pulseira Consagrada Preto Velho com Pingente Niquelado | D12: 6 | E12: Item confecionado artesanalmente pelo Ateliê Arroboboi para a egrégora de Preto Velho. Produto final de alta qualidade. | F12: 84.5 | G12: https://www.instagram.com/arroboboi.atelie/p/post_11/ | H12: 16 | I12: TRUE | J12: 45820
A13: 12 | B13: ARB-C1-0012 | C13: Chicote de Firma Caboclo Edição Limitada Arroboboi | D13: 1 | E13: Item confecionado artesanalmente pelo Ateliê Arroboboi para a egrégora de Caboclo. Produto final de alta qualidade. | F13: 89 | G13: https://www.instagram.com/arroboboi.atelie/p/post_12/ | H13: 17 | I13: TRUE | J13: 45821
... A501: 500 | B501: ARB-C3-0500 | C501: Taça Rituística Cigano Edição Limitada Arroboboi | D501: 3 | E501: Item confecionado artesanalmente pelo Ateliê Arroboboi para a egrégora de Cigano. Produto final de alta qualidade. | F501: 125 | G501: https://www.instagram.com/arroboboi.atelie/p/post_500/ | H501: 5 | I501: TRUE | J501: 46009

Sheet Composicao_Produto
A1: id_produto | B1: id_materia_prima | C1: quantidade_usada
A2: 1 | B2: 1 | C2: 1.5
A3: 2 | B3: 2 | C3: 2
A4: 3 | B4: 3 | C4: 2.5
A5: 4 | B5: 4 | C5: 3
A6: 5 | B6: 5 | C6: 1
A7: 6 | B7: 6 | C7: 1.5
A8: 7 | B8: 7 | C8: 2
A9: 8 | B9: 8 | C9: 2.5
A10: 9 | B10: 9 | C10: 3
A11: 10 | B11: 10 | C11: 1
A12: 11 | B12: 11 | C12: 1.5
A13: 12 | B13: 12 | C13: 2
... A501: 500 | B501: 500 | C501: 1

Sheet Clientes
A1: id_cliente | B1: nome | C1: whatsapp | D1: instagram_handle | E1: email | F1: cidade | G1: estado | H1: data_cadastro
A2: 1 | B2: Carlos Santos | C2: (11) 990000001 | D2: @cliente_axe_1 | E2: cliente1@email.com | F2: Santo André | G2: SP | H2: 45718
A3: 2 | B3: Beatriz Oliveira | C3: (11) 990000002 | D3: @cliente_axe_2 | E3: cliente2@email.com | F3: São Bernardo do Campo | G3: SP | H3: 45719
A4: 3 | B4: Lucas Souza | C4: (11) 990000003 | D4: @cliente_axe_3 | E4: cliente3@email.com | F4: Osasco | G4: SP | H4: 45720
A5: 4 | B5: Fernanda Rodrigues | C5: (11) 990000004 | D5: @cliente_axe_4 | E5: cliente4@email.com | F5: Campinas | G5: SP | H5: 45721
A6: 5 | B6: Gabriel Ferreira | C6: (11) 990000005 | D6: @cliente_axe_5 | E6: cliente5@email.com | F6: Rio de Janeiro | G6: RJ | H6: 45722
A7: 6 | B7: Juliana Alves | C7: (11) 990000006 | D7: @cliente_axe_6 | E7: cliente6@email.com | F7: Niterói | G7: RJ | H7: 45723
A8: 7 | B8: Rodrigo Pereira | C8: (11) 990000007 | D8: @cliente_axe_7 | E8: cliente7@email.com | F8: Salvador | G8: BA | H8: 45724
A9: 8 | B9: Camila Lima | C9: (11) 990000008 | D9: @cliente_axe_8 | E9: cliente8@email.com | F9: Curitiba | G9: PR | H9: 45725
A10: 9 | B10: Thiago Gomes | C10: (11) 990000009 | D10: @cliente_axe_9 | E10: cliente9@email.com | F10: Porto Alegre | G10: RS | H10: 45726
A11: 10 | B11: Mariana Costa | C11: (11) 990000010 | D11: @cliente_axe_10 | E11: cliente10@email.com | F11: São Paulo | G11: SP | H11: 45727
A12: 11 | B12: Vinicius Ribeiro | C12: (11) 990000011 | D12: @cliente_axe_11 | E12: cliente11@email.com | F12: Santo André | G12: SP | H12: 45728
A13: 12 | B13: Patricia Martins | C13: (11) 990000012 | D13: @cliente_axe_12 | E13: cliente12@email.com | F13: São Bernardo do Campo | G13: SP | H13: 45729
... A501: 500 | B501: Gabriel Costa | C501: (11) 990000500 | D501: @cliente_axe_500 | E501: cliente500@email.com | F501: São Paulo | G501: SP | H501: 45817

Sheet Pedidos
A1: id_pedido | B1: id_cliente | C1: tipo | D1: status | E1: valor_total | F1: desconto | G1: data_criacao | H1: data_entrega_prevista | I1: observacoes
A2: 1 | B2: 2 | C2: Pedido | D2: Aprovado | E2: 65 | F2: 0 | G2: 46024 | H2: 46032 | I2: Pedido/Orçamento referente a personalização de guia/artefato espiritual nº 1
A3: 2 | B3: 3 | C3: Orcamento | D3: Em Producao | E3: 80 | F3: 0 | G3: 46025 | H3: 46034 | I3: Pedido/Orçamento referente a personalização de guia/artefato espiritual nº 2
A4: 3 | B4: 4 | C4: Pedido | D4: Enviado | E4: 95 | F4: 0 | G4: 46026 | H4: 46036 | I4: Pedido/Orçamento referente a personalização de guia/artefato espiritual nº 3
A5: 4 | B5: 5 | C5: Orcamento | D5: Entregue | E5: 110 | F5: 0 | G5: 46027 | H5: 46038 | I5: Pedido/Orçamento referente a personalização de guia/artefato espiritual nº 4
A6: 5 | B6: 6 | C6: Pedido | D6: Cancelado | E6: 125 | F6: 10 | G6: 46028 | H6: 46040 | I6: Pedido/Orçamento referente a personalização de guia/artefato espiritual nº 5
A7: 6 | B7: 7 | C7: Orcamento | D7: Pendente | E7: 140 | F7: 0 | G7: 46029 | H7: 46042 | I7: Pedido/Orçamento referente a personalização de guia/artefato espiritual nº 6
A8: 7 | B8: 8 | C8: Pedido | D8: Aprovado | E8: 155 | F8: 0 | G8: 46030 | H8: 46044 | I8: Pedido/Orçamento referente a personalização de guia/artefato espiritual nº 7
A9: 8 | B9: 9 | C9: Orcamento | D9: Em Producao | E9: 170 | F9: 0 | G9: 46031 | H9: 46046 | I9: Pedido/Orçamento referente a personalização de guia/artefato espiritual nº 8
A10: 9 | B10: 10 | C10: Pedido | D10: Enviado | E10: 185 | F10: 0 | G10: 46032 | H10: 46048 | I10: Pedido/Orçamento referente a personalização de guia/artefato espiritual nº 9
A11: 10 | B11: 11 | C11: Orcamento | D11: Entregue | E11: 200 | F11: 10 | G11: 46033 | H11: 46050 | I11: Pedido/Orçamento referente a personalização de guia/artefato espiritual nº 10
A12: 11 | B12: 12 | C12: Pedido | D12: Cancelado | E12: 215 | F12: 0 | G12: 46034 | H12: 46052 | I12: Pedido/Orçamento referente a personalização de guia/artefato espiritual nº 11
A13: 12 | B13: 13 | C13: Orcamento | D13: Pendente | E13: 230 | F13: 0 | G13: 46035 | H13: 46054 | I13: Pedido/Orçamento referente a personalização de guia/artefato espiritual nº 12
... A501: 500 | B501: 1 | C501: Orcamento | D501: Em Producao | E501: 350 | F501: 10 | G501: 46163 | H501: 46175 | I501: Pedido/Orçamento referente a personalização de guia/artefato espiritual nº 500

Sheet Itens_Pedido
A1: id_item_pedido | B1: id_pedido | C1: id_produto | D1: quantidade | E1: preco_unitario | F1: subtotal
A2: 1 | B2: 1 | C2: 2 | D2: 2 | E2: 40 | F2: =D2*E2
A3: 2 | B3: 2 | C3: 3 | D3: 3 | E3: 45 | F3: =D3*E3
A4: 3 | B4: 3 | C4: 4 | D4: 4 | E4: 50 | F4: =D4*E4
A5: 4 | B5: 4 | C5: 5 | D5: 1 | E5: 55 | F5: =D5*E5
A6: 5 | B6: 5 | C6: 6 | D6: 2 | E6: 60 | F6: =D6*E6
A7: 6 | B7: 6 | C7: 7 | D7: 3 | E7: 65 | F7: =D7*E7
A8: 7 | B8: 7 | C8: 8 | D8: 4 | E8: 70 | F8: =D8*E8
A9: 8 | B9: 8 | C9: 9 | D9: 1 | E9: 75 | F9: =D9*E9
A10: 9 | B10: 9 | C10: 10 | D10: 2 | E10: 80 | F10: =D10*E10
A11: 10 | B11: 10 | C11: 11 | D11: 3 | E11: 85 | F11: =D11*E11
A12: 11 | B12: 11 | C12: 12 | D12: 4 | E12: 90 | F12: =D12*E12
A13: 12 | B13: 12 | C13: 13 | D13: 1 | E13: 95 | F13: =D13*E13
... A501: 500 | B501: 500 | C501: 1 | D501: 1 | E501: 35 | F501: =D501*E501
